zerocopy/__init__.py
zerocopy/invoke.py
zerocopy/rewrite.py
zerocopy-0.1.0.dist-info/METADATA
zerocopy-0.1.0.dist-info/WHEEL
zerocopy-0.1.0.dist-info/top_level.txt
zerocopy-0.1.0.dist-info/RECORD
