Metadata-Version: 2.1
Name: zerocopy
Version: 0.1.0
Summary: Zero-copy model loading for PyTorch and Ray.
Home-page: https://github.com/frreiss/zero-copy-model-loading
Author: IBM
Author-email: frreiss@us.ibm.com
License: UNKNOWN
Platform: UNKNOWN
Classifier: Programming Language :: Python :: 3
Classifier: License :: OSI Approved :: Apache Software License
Classifier: Operating System :: OS Independent
Classifier: Topic :: Scientific/Engineering
Requires-Python: >=3.7
Requires-Dist: ray
Requires-Dist: torch
